{"68644":{"l":"green","s":0,"r":[["insufficient_data",0]],"m":{"dom":126.0},"st":"NE"},"68850":{"l":"red","s":5,"r":[["price_falling_fast",-0.143],["dom_stretching",41.0],["inventory_surge",1.625]],"m":{"mos":2.471,"spy":-0.143,"dom":86.0,"domy":41.0,"invy":1.625},"st":"NE"},"68466":{"l":"green","s":1,"r":[["inventory_surge",1.0]],"m":{"mos":4.0,"spy":0.102,"dom":6.0,"domy":-94.5,"invy":1.0},"st":"NE"},"68402":{"l":"green","s":1,"r":[["dom_stretching",128.0]],"m":{"spy":0.547,"dom":140.0,"domy":128.0},"st":"NE"},"68347":{"l":"yellow","s":3,"r":[["price_falling_fast",-0.17]],"m":{"mos":0.333,"spy":-0.17,"dom":6.0,"domy":-36.0,"invy":0.333},"st":"NE"},"68349":{"l":"green","s":0,"r":[],"m":{"mos":1.0,"spy":1.022,"dom":4.0,"domy":-2.0,"invy":-0.5},"st":"NE"},"68463":{"l":"green","s":1,"r":[["dom_stretching",10.0]],"m":{"mos":0.667,"spy":0.385,"dom":14.0,"domy":10.0},"st":"NE"},"68040":{"l":"green","s":0,"r":[["insufficient_data",0]],"m":{"dom":4.0},"st":"NE"},"68956":{"l":"green","s":0,"r":[["insufficient_data",1]],"m":{"mos":2.0,"dom":2.0},"st":"NE"},"68041":{"l":"green","s":0,"r":[],"m":{"spy":0.065,"dom":35.0,"domy":0.5},"st":"NE"},"68628":{"l":"green","s":0,"r":[["insufficient_data",1]],"m":{"mos":4.0,"dom":4.0},"st":"NE"},"68767":{"l":"green","s":1,"r":[["dom_stretching",25.0]],"m":{"mos":1.0,"spy":0.61,"dom":32.0,"domy":25.0,"invy":0.0},"st":"NE"},"68601":{"l":"red","s":4,"r":[["price_falling_fast",-0.091],["dom_stretching",16.0]],"m":{"mos":1.126,"spy":-0.091,"dom":42.0,"domy":16.0,"invy":0.032},"st":"NE"},"68801":{"l":"green","s":0,"r":[],"m":{"mos":0.701,"spy":0.054,"dom":24.0,"domy":-5.5,"invy":-0.113},"st":"NE"},"68341":{"l":"green","s":0,"r":[["insufficient_data",1]],"m":{"mos":1.0,"dom":145.0},"st":"NE"},"68107":{"l":"yellow","s":2,"r":[["price_falling",-0.045]],"m":{"mos":0.333,"spy":-0.045,"dom":19.5,"domy":-2.0,"invy":-0.227},"st":"NE"},"68521":{"l":"yellow","s":3,"r":[["price_falling_fast",-0.056]],"m":{"mos":0.468,"spy":-0.056,"dom":24.0,"domy":3.5,"invy":-0.175},"st":"NE"},"68127":{"l":"green","s":0,"r":[],"m":{"mos":0.204,"spy":0.046,"dom":12.0,"domy":0.0,"invy":-0.154},"st":"NE"},"68029":{"l":"yellow","s":3,"r":[["price_falling_fast",-0.465]],"m":{"spy":-0.465,"dom":92.5,"domy":-19.0},"st":"NE"},"68310":{"l":"green","s":0,"r":[],"m":{"mos":0.977,"spy":-0.012,"dom":39.0,"domy":-16.0,"invy":0.075},"st":"NE"},"68779":{"l":"red","s":4,"r":[["price_falling_fast",-0.099],["dom_stretching",97.5]],"m":{"mos":1.0,"spy":-0.099,"dom":151.5,"domy":97.5,"invy":0.0},"st":"NE"},"68069":{"l":"green","s":1,"r":[["dom_stretching",25.5]],"m":{"mos":0.455,"spy":1.918,"dom":45.0,"domy":25.5,"invy":-0.583},"st":"NE"},"68832":{"l":"green","s":0,"r":[],"m":{"mos":1.0,"spy":0.98,"dom":29.0,"domy":0.0,"invy":-0.25},"st":"NE"},"68007":{"l":"yellow","s":3,"r":[["price_falling_fast",-0.074]],"m":{"mos":0.644,"spy":-0.074,"dom":116.5,"domy":14.0,"invy":-0.469},"st":"NE"},"68924":{"l":"red","s":4,"r":[["price_falling_fast",-0.493],["dom_stretching",41.0]],"m":{"mos":1.0,"spy":-0.493,"dom":45.0,"domy":41.0,"invy":-0.667},"st":"NE"},"68870":{"l":"green","s":0,"r":[["insufficient_data",0]],"m":{"dom":14.0},"st":"NE"},"68065":{"l":"red","s":4,"r":[["price_falling_fast",-0.328],["dom_stretching",80.0]],"m":{"mos":1.5,"spy":-0.328,"dom":86.0,"domy":80.0,"invy":-0.25},"st":"NE"},"68058":{"l":"green","s":0,"r":[["insufficient_data",0]],"m":{"dom":2.0},"st":"NE"},"68741":{"l":"red","s":4,"r":[["price_falling_fast",-0.107],["dom_stretching",25.0]],"m":{"spy":-0.107,"dom":55.0,"domy":25.0},"st":"NE"},"68510":{"l":"yellow","s":2,"r":[["price_falling",-0.028]],"m":{"mos":0.298,"spy":-0.028,"dom":10.0,"domy":-13.0,"invy":-0.444},"st":"NE"},"68506":{"l":"green","s":1,"r":[["dom_stretching",7.0]],"m":{"mos":0.284,"spy":0.063,"dom":22.0,"domy":7.0,"invy":-0.365},"st":"NE"},"68110":{"l":"green","s":0,"r":[],"m":{"mos":1.636,"spy":0.172,"dom":75.0,"domy":15.0,"invy":0.5},"st":"NE"},"68462":{"l":"yellow","s":2,"r":[["price_falling",-0.049]],"m":{"mos":0.857,"spy":-0.049,"dom":23.5,"domy":5.5,"invy":-0.429},"st":"NE"},"68415":{"l":"yellow","s":3,"r":[["price_falling_fast",-0.212]],"m":{"spy":-0.212,"dom":44.0,"domy":-119.0},"st":"NE"},"68152":{"l":"green","s":0,"r":[],"m":{"mos":0.737,"spy":0.068,"dom":20.0,"domy":-9.0,"invy":0.077},"st":"NE"},"68523":{"l":"green","s":0,"r":[],"m":{"mos":0.667,"spy":0.082,"dom":98.5,"domy":-70.5,"invy":-0.429},"st":"NE"},"68937":{"l":"yellow","s":3,"r":[["supply_high",4.6],["inventory_surge",1.091]],"m":{"mos":4.6,"spy":0.091,"dom":16.0,"domy":-41.0,"invy":1.091},"st":"NE"},"69130":{"l":"yellow","s":2,"r":[["dom_stretching",11.5],["inventory_surge",2.167]],"m":{"mos":3.167,"spy":0.386,"dom":27.5,"domy":11.5,"invy":2.167},"st":"NE"},"68137":{"l":"green","s":1,"r":[["dom_stretching",4.0]],"m":{"mos":0.212,"spy":0.041,"dom":12.5,"domy":4.0,"invy":-0.561},"st":"NE"},"68028":{"l":"green","s":0,"r":[],"m":{"mos":0.812,"spy":-0.004,"dom":98.0,"domy":-42.0,"invy":-0.163},"st":"NE"},"68128":{"l":"yellow","s":3,"r":[["price_falling",-0.039],["dom_stretching",6.0]],"m":{"mos":0.123,"spy":-0.039,"dom":16.0,"domy":6.0,"invy":-0.533},"st":"NE"},"68873":{"l":"green","s":1,"r":[["dom_stretching",38.5]],"m":{"mos":0.5,"spy":0.013,"dom":48.5,"domy":38.5,"invy":-0.6},"st":"NE"},"68524":{"l":"green","s":0,"r":[],"m":{"spy":-0.018,"dom":13.0,"domy":-9.0},"st":"NE"},"69138":{"l":"yellow","s":2,"r":[["price_falling",-0.032]],"m":{"mos":1.214,"spy":-0.032,"dom":33.0,"domy":-8.0,"invy":0.062},"st":"NE"},"68522":{"l":"green","s":1,"r":[["dom_stretching",9.0]],"m":{"mos":0.178,"spy":0.031,"dom":19.0,"domy":9.0,"invy":-0.68},"st":"NE"},"68840":{"l":"yellow","s":3,"r":[["price_falling_fast",-0.406]],"m":{"mos":1.25,"spy":-0.406,"dom":16.0,"domy":-17.5,"invy":0.0},"st":"NE"},"68784":{"l":"red","s":4,"r":[["price_falling_fast",-0.328],["dom_stretching",21.0]],"m":{"mos":1.0,"spy":-0.328,"dom":49.0,"domy":21.0},"st":"NE"},"68776":{"l":"green","s":0,"r":[],"m":{"mos":0.64,"spy":-0.007,"dom":22.0,"domy":-23.0,"invy":0.067},"st":"NE"},"68528":{"l":"yellow","s":3,"r":[["price_falling",-0.025],["dom_stretching",17.0]],"m":{"mos":0.375,"spy":-0.025,"dom":32.0,"domy":17.0,"invy":-0.478},"st":"NE"},"68135":{"l":"green","s":0,"r":[],"m":{"mos":0.32,"spy":0.147,"dom":20.0,"domy":5.0,"invy":-0.5},"st":"NE"},"68016":{"l":"red","s":4,"r":[["price_falling_fast",-0.134],["dom_stretching",15.0]],"m":{"spy":-0.134,"dom":19.0,"domy":15.0},"st":"NE"},"68023":{"l":"green","s":1,"r":[["dom_stretching",66.0]],"m":{"mos":0.667,"spy":0.973,"dom":70.0,"domy":66.0,"invy":-0.667},"st":"NE"},"68046":{"l":"green","s":0,"r":[],"m":{"mos":0.606,"spy":0.069,"dom":57.0,"domy":-21.0,"invy":-0.455},"st":"NE"},"68824":{"l":"green","s":0,"r":[],"m":{"mos":2.0,"spy":9.678,"dom":5.0,"domy":-234.0,"invy":-0.333},"st":"NE"},"68037":{"l":"green","s":0,"r":[],"m":{"mos":0.75,"spy":0.563,"dom":34.0,"domy":-5.0,"invy":-0.4},"st":"NE"},"68147":{"l":"green","s":1,"r":[["dom_stretching",6.5]],"m":{"mos":0.767,"spy":-0.013,"dom":20.5,"domy":6.5,"invy":0.278},"st":"NE"},"68858":{"l":"green","s":0,"r":[["insufficient_data",0]],"m":{"dom":28.0},"st":"NE"},"68328":{"l":"yellow","s":3,"r":[["price_falling_fast",-0.419]],"m":{"spy":-0.419,"dom":5.0,"domy":1.0},"st":"NE"},"68621":{"l":"green","s":1,"r":[["dom_stretching",70.0]],"m":{"spy":1.189,"dom":90.0,"domy":70.0},"st":"NE"},"68514":{"l":"green","s":1,"r":[["dom_stretching",26.0]],"m":{"mos":0.5,"spy":0.508,"dom":69.0,"domy":26.0,"invy":-0.25},"st":"NE"},"68423":{"l":"green","s":1,"r":[["dom_stretching",58.5]],"m":{"spy":0.417,"dom":72.5,"domy":58.5},"st":"NE"},"68307":{"l":"green","s":1,"r":[["dom_stretching",141.0]],"m":{"mos":1.0,"spy":0.583,"dom":168.0,"domy":141.0},"st":"NE"},"68631":{"l":"green","s":0,"r":[["insufficient_data",0]],"m":{"dom":15.0},"st":"NE"},"68057":{"l":"yellow","s":2,"r":[["dom_stretching",74.0],["inventory_surge",0.75]],"m":{"mos":2.333,"spy":0.055,"dom":143.0,"domy":74.0,"invy":0.75},"st":"NE"},"68526":{"l":"green","s":0,"r":[],"m":{"mos":0.696,"spy":-0.008,"dom":61.0,"domy":16.0,"invy":-0.467},"st":"NE"},"68136":{"l":"green","s":0,"r":[],"m":{"mos":0.441,"spy":0.074,"dom":42.0,"domy":-1.0,"invy":-0.571},"st":"NE"},"68701":{"l":"green","s":0,"r":[],"m":{"mos":0.882,"spy":0.129,"dom":34.5,"domy":4.5,"invy":-0.176},"st":"NE"},"68649":{"l":"yellow","s":2,"r":[["dom_stretching",23.5],["inventory_surge",1.25]],"m":{"mos":3.0,"spy":2.529,"dom":42.0,"domy":23.5,"invy":1.25},"st":"NE"},"68731":{"l":"yellow","s":3,"r":[["price_falling_fast",-0.131]],"m":{"mos":1.0,"spy":-0.131,"dom":37.0,"domy":-54.0,"invy":-0.5},"st":"NE"},"69123":{"l":"green","s":0,"r":[["insufficient_data",1]],"m":{"mos":0.333,"dom":35.0},"st":"NE"},"68033":{"l":"green","s":0,"r":[["insufficient_data",1]],"m":{"mos":1.0,"dom":9.0},"st":"NE"},"68005":{"l":"green","s":0,"r":[],"m":{"mos":0.224,"spy":0.033,"dom":13.0,"domy":1.0,"invy":-0.318},"st":"NE"},"68117":{"l":"yellow","s":3,"r":[["price_falling_fast",-0.09]],"m":{"mos":0.167,"spy":-0.09,"dom":12.5,"domy":0.5,"invy":-0.286},"st":"NE"},"68073":{"l":"green","s":1,"r":[["inventory_surge",2.0]],"m":{"mos":1.5,"spy":0.234,"dom":39.5,"domy":-16.0,"invy":2.0},"st":"NE"},"69101":{"l":"green","s":0,"r":[],"m":{"mos":0.869,"spy":0.219,"dom":25.0,"domy":-18.5,"invy":0.123},"st":"NE"},"68131":{"l":"green","s":1,"r":[["dom_stretching",26.5]],"m":{"mos":1.069,"spy":0.008,"dom":48.0,"domy":26.5,"invy":0.033},"st":"NE"},"68428":{"l":"green","s":0,"r":[["insufficient_data",1]],"m":{"mos":0.4,"dom":45.0},"st":"NE"},"68517":{"l":"yellow","s":3,"r":[["price_falling_fast",-0.142]],"m":{"mos":1.0,"spy":-0.142,"dom":38.0,"domy":-223.0},"st":"NE"},"68122":{"l":"green","s":1,"r":[["dom_stretching",8.0]],"m":{"mos":0.264,"spy":0.025,"dom":17.0,"domy":8.0,"invy":-0.333},"st":"NE"},"68836":{"l":"yellow","s":3,"r":[["price_falling_fast",-0.589]],"m":{"spy":-0.589,"dom":52.0,"domy":-27.0},"st":"NE"},"68123":{"l":"green","s":0,"r":[],"m":{"mos":0.359,"spy":0.043,"dom":14.0,"domy":-4.0,"invy":-0.108},"st":"NE"},"68976":{"l":"green","s":0,"r":[["insufficient_data",0]],"m":{"dom":24.0},"st":"NE"},"68520":{"l":"green","s":0,"r":[],"m":{"mos":1.786,"spy":0.136,"dom":159.0,"domy":15.0,"invy":-0.528},"st":"NE"},"69361":{"l":"green","s":0,"r":[],"m":{"mos":1.312,"spy":0.471,"dom":25.0,"domy":-15.0,"invy":-0.087},"st":"NE"},"68950":{"l":"green","s":0,"r":[],"m":{"mos":1.0,"spy":5.25,"dom":5.0,"domy":-15.0,"invy":0.0},"st":"NE"},"68134":{"l":"green","s":0,"r":[],"m":{"mos":0.269,"spy":0.047,"dom":11.0,"domy":-1.5,"invy":0.136},"st":"NE"},"68503":{"l":"green","s":1,"r":[["dom_stretching",12.0]],"m":{"mos":0.447,"spy":0.026,"dom":34.0,"domy":12.0,"invy":0.167},"st":"NE"},"68358":{"l":"green","s":0,"r":[],"m":{"mos":0.167,"spy":0.298,"dom":32.0,"domy":-21.0,"invy":-0.8},"st":"NE"},"68360":{"l":"yellow","s":3,"r":[["price_falling_fast",-0.356]],"m":{"spy":-0.356,"dom":186.0,"domy":-9.0},"st":"NE"},"68743":{"l":"red","s":4,"r":[["price_falling_fast",-0.053],["dom_stretching",18.0]],"m":{"mos":0.5,"spy":-0.053,"dom":36.0,"domy":18.0,"invy":-0.5},"st":"NE"},"68034":{"l":"yellow","s":3,"r":[["price_falling_fast",-0.413]],"m":{"spy":-0.413,"dom":2.0,"domy":-6.0},"st":"NE"},"68758":{"l":"yellow","s":3,"r":[["price_falling_fast",-0.344]],"m":{"spy":-0.344,"dom":44.0,"domy":-44.0},"st":"NE"},"68015":{"l":"red","s":4,"r":[["price_falling_fast",-0.091],["dom_stretching",11.0]],"m":{"mos":1.333,"spy":-0.091,"dom":36.0,"domy":11.0},"st":"NE"},"68044":{"l":"red","s":4,"r":[["price_falling_fast",-0.103],["dom_stretching",28.5]],"m":{"mos":3.0,"spy":-0.103,"dom":37.0,"domy":28.5},"st":"NE"},"69163":{"l":"green","s":0,"r":[["insufficient_data",1]],"m":{"mos":1.5,"dom":23.0},"st":"NE"},"68025":{"l":"yellow","s":2,"r":[["price_falling",-0.05]],"m":{"mos":0.626,"spy":-0.05,"dom":44.0,"domy":0.0,"invy":-0.061},"st":"NE"},"68847":{"l":"green","s":0,"r":[],"m":{"mos":0.339,"spy":0.153,"dom":19.0,"domy":-9.5,"invy":0.0},"st":"NE"},"68030":{"l":"green","s":1,"r":[["dom_stretching",28.0]],"m":{"mos":1.5,"spy":0.009,"dom":32.0,"domy":28.0},"st":"NE"},"69345":{"l":"green","s":0,"r":[],"m":{"mos":1.0,"spy":0.6,"dom":30.0,"domy":-133.0},"st":"NE"},"68108":{"l":"green","s":0,"r":[],"m":{"mos":0.857,"spy":0.187,"dom":29.0,"domy":1.0,"invy":0.043},"st":"NE"},"68059":{"l":"green","s":1,"r":[["dom_stretching",11.5]],"m":{"mos":0.889,"spy":0.18,"dom":22.0,"domy":11.5,"invy":0.143},"st":"NE"},"68633":{"l":"green","s":0,"r":[],"m":{"mos":0.5,"spy":0.163,"dom":20.5,"domy":-32.5},"st":"NE"},"68748":{"l":"red","s":5,"r":[["price_falling_fast",-0.129],["dom_stretching",23.0],["inventory_surge",0.667]],"m":{"mos":1.25,"spy":-0.129,"dom":46.0,"domy":23.0,"invy":0.667},"st":"NE"},"68438":{"l":"green","s":0,"r":[],"m":{"spy":0.238,"dom":2.0,"domy":-60.0},"st":"NE"},"68106":{"l":"green","s":1,"r":[["dom_stretching",17.0]],"m":{"mos":0.247,"spy":0.024,"dom":26.0,"domy":17.0,"invy":-0.486},"st":"NE"},"68164":{"l":"green","s":1,"r":[["dom_stretching",6.5]],"m":{"mos":0.214,"spy":0.096,"dom":19.5,"domy":6.5,"invy":-0.471},"st":"NE"},"68404":{"l":"green","s":0,"r":[],"m":{"mos":1.0,"spy":0.02,"dom":20.0,"domy":-18.0,"invy":0.0},"st":"NE"},"68002":{"l":"green","s":0,"r":[],"m":{"mos":0.5,"spy":0.077,"dom":19.0,"domy":-80.0,"invy":-0.333},"st":"NE"},"68118":{"l":"green","s":0,"r":[],"m":{"mos":0.344,"spy":-0.007,"dom":10.5,"domy":-12.5,"invy":-0.312},"st":"NE"},"68003":{"l":"yellow","s":2,"r":[["price_falling",-0.026]],"m":{"mos":2.0,"spy":-0.026,"dom":14.0,"domy":-20.0,"invy":0.5},"st":"NE"},"68102":{"l":"green","s":1,"r":[["dom_stretching",28.5]],"m":{"mos":2.5,"spy":0.067,"dom":36.5,"domy":28.5,"invy":0.429},"st":"NE"},"68409":{"l":"green","s":0,"r":[["insufficient_data",1]],"m":{"mos":0.2,"dom":53.0},"st":"NE"},"68869":{"l":"red","s":5,"r":[["price_falling_fast",-0.183],["dom_stretching",103.5],["inventory_surge",1.0]],"m":{"mos":3.0,"spy":-0.183,"dom":150.0,"domy":103.5,"invy":1.0},"st":"NE"},"68130":{"l":"green","s":0,"r":[],"m":{"mos":0.439,"spy":-0.015,"dom":19.0,"domy":0.0,"invy":-0.342},"st":"NE"},"68068":{"l":"green","s":0,"r":[["insufficient_data",0]],"m":{"dom":40.0},"st":"NE"},"68154":{"l":"yellow","s":2,"r":[["price_falling",-0.025]],"m":{"mos":0.403,"spy":-0.025,"dom":14.0,"domy":-4.0,"invy":-0.306},"st":"NE"},"68112":{"l":"green","s":1,"r":[["dom_stretching",12.0]],"m":{"mos":0.471,"spy":0.031,"dom":25.0,"domy":12.0,"invy":0.333},"st":"NE"},"68116":{"l":"green","s":1,"r":[["dom_stretching",8.0]],"m":{"mos":0.19,"spy":-0.003,"dom":25.0,"domy":8.0,"invy":-0.737},"st":"NE"},"68318":{"l":"green","s":0,"r":[["insufficient_data",0]],"m":{"dom":121.0},"st":"NE"},"68357":{"l":"green","s":0,"r":[["insufficient_data",1]],"m":{"mos":2.0,"dom":8.0},"st":"NE"},"68505":{"l":"green","s":0,"r":[],"m":{"mos":0.29,"spy":0.071,"dom":13.0,"domy":-2.5,"invy":-0.259},"st":"NE"},"68124":{"l":"yellow","s":2,"r":[["price_falling",-0.022]],"m":{"mos":0.387,"spy":-0.022,"dom":22.0,"domy":-9.0,"invy":-0.455},"st":"NE"},"68642":{"l":"green","s":1,"r":[["dom_stretching",61.0]],"m":{"mos":1.0,"spy":0.082,"dom":194.0,"domy":61.0,"invy":0.333},"st":"NE"},"68142":{"l":"yellow","s":3,"r":[["price_falling_fast",-0.075]],"m":{"mos":0.277,"spy":-0.075,"dom":52.5,"domy":-2.5,"invy":-0.64},"st":"NE"},"68826":{"l":"green","s":0,"r":[],"m":{"mos":0.714,"spy":1.0,"dom":7.0,"domy":-118.0,"invy":0.0},"st":"NE"},"68018":{"l":"green","s":0,"r":[["insufficient_data",1]],"m":{"mos":1.0,"dom":6.0},"st":"NE"},"68955":{"l":"red","s":5,"r":[["price_falling_fast",-0.353],["dom_stretching",27.0],["inventory_surge",3.0]],"m":{"mos":1.0,"spy":-0.353,"dom":47.0,"domy":27.0,"invy":3.0},"st":"NE"},"68770":{"l":"green","s":1,"r":[["dom_stretching",34.5]],"m":{"mos":1.0,"spy":0.111,"dom":63.5,"domy":34.5,"invy":0.0},"st":"NE"},"68072":{"l":"green","s":0,"r":[["insufficient_data",0]],"m":{"dom":258.0},"st":"NE"},"68516":{"l":"green","s":0,"r":[],"m":{"mos":0.495,"spy":-0.018,"dom":24.5,"domy":6.5,"invy":-0.353},"st":"NE"},"68838":{"l":"green","s":0,"r":[["insufficient_data",0]],"m":{"dom":434.5},"st":"NE"},"68816":{"l":"green","s":0,"r":[["insufficient_data",0]],"m":{"dom":98.0},"st":"NE"},"68063":{"l":"green","s":0,"r":[["insufficient_data",1]],"m":{"mos":1.0,"dom":52.0},"st":"NE"},"68017":{"l":"green","s":0,"r":[],"m":{"mos":1.0,"spy":0.312,"dom":17.0,"domy":-5.5,"invy":-0.5},"st":"NE"},"68066":{"l":"green","s":0,"r":[],"m":{"mos":0.857,"spy":0.237,"dom":31.0,"domy":-1.0,"invy":-0.333},"st":"NE"},"68434":{"l":"green","s":0,"r":[],"m":{"mos":0.345,"spy":0.091,"dom":42.0,"domy":11.0,"invy":-0.375},"st":"NE"},"68339":{"l":"green","s":0,"r":[],"m":{"mos":1.0,"spy":0.926,"dom":15.0,"domy":-2.0,"invy":-0.2},"st":"NE"},"68845":{"l":"green","s":1,"r":[["dom_stretching",22.0]],"m":{"mos":0.688,"spy":0.168,"dom":29.5,"domy":22.0,"invy":0.467},"st":"NE"},"68144":{"l":"green","s":0,"r":[],"m":{"mos":0.13,"spy":-0.01,"dom":7.0,"domy":-1.0,"invy":-0.667},"st":"NE"},"69165":{"l":"yellow","s":3,"r":[["price_falling_fast",-0.129]],"m":{"mos":0.5,"spy":-0.129,"dom":13.0,"domy":-33.5,"invy":-0.5},"st":"NE"},"68407":{"l":"green","s":0,"r":[["insufficient_data",1]],"m":{"mos":1.0,"dom":100.0},"st":"NE"},"68959":{"l":"green","s":0,"r":[],"m":{"mos":0.667,"spy":0.008,"dom":27.5,"domy":2.5,"invy":-0.556},"st":"NE"},"68372":{"l":"green","s":1,"r":[["dom_stretching",17.5]],"m":{"mos":0.947,"spy":0.09,"dom":60.0,"domy":17.5,"invy":0.125},"st":"NE"},"68331":{"l":"yellow","s":3,"r":[["price_falling_fast",-0.461]],"m":{"spy":-0.461,"dom":9.0,"domy":-60.5},"st":"NE"},"68301":{"l":"yellow","s":3,"r":[["price_falling_fast",-0.116]],"m":{"mos":0.5,"spy":-0.116,"dom":28.5,"domy":7.5,"invy":-0.667},"st":"NE"},"68455":{"l":"green","s":0,"r":[["insufficient_data",1]],"m":{"mos":3.0,"dom":195.0},"st":"NE"},"68810":{"l":"green","s":0,"r":[["insufficient_data",0]],"m":{"dom":215.0},"st":"NE"},"68313":{"l":"green","s":0,"r":[["insufficient_data",1]],"m":{"mos":2.0,"dom":25.5},"st":"NE"},"68532":{"l":"yellow","s":3,"r":[["price_falling_fast",-0.105]],"m":{"mos":1.0,"spy":-0.105,"dom":121.0,"domy":-164.0,"invy":0.0},"st":"NE"},"68157":{"l":"yellow","s":3,"r":[["price_falling_fast",-0.207]],"m":{"mos":0.188,"spy":-0.207,"dom":26.0,"domy":-4.0,"invy":-0.824},"st":"NE"},"68114":{"l":"yellow","s":3,"r":[["price_falling_fast",-0.057]],"m":{"mos":0.571,"spy":-0.057,"dom":7.0,"domy":-7.0,"invy":-0.333},"st":"NE"},"68502":{"l":"green","s":1,"r":[["dom_stretching",11.0]],"m":{"mos":0.472,"spy":0.076,"dom":31.0,"domy":11.0,"invy":-0.192},"st":"NE"},"68647":{"l":"green","s":1,"r":[["dom_stretching",53.0]],"m":{"spy":0.609,"dom":60.0,"domy":53.0},"st":"NE"},"68368":{"l":"yellow","s":3,"r":[["price_falling_fast",-0.226]],"m":{"spy":-0.226,"dom":6.0,"domy":-24.0},"st":"NE"},"68507":{"l":"yellow","s":3,"r":[["price_falling",-0.027],["dom_stretching",6.0]],"m":{"mos":0.312,"spy":-0.027,"dom":19.0,"domy":6.0,"invy":-0.355},"st":"NE"},"68050":{"l":"red","s":4,"r":[["price_falling_fast",-0.33],["dom_stretching",33.0]],"m":{"mos":1.0,"spy":-0.33,"dom":57.0,"domy":33.0},"st":"NE"},"68132":{"l":"red","s":4,"r":[["price_falling_fast",-0.086],["dom_stretching",17.0]],"m":{"mos":0.6,"spy":-0.086,"dom":26.0,"domy":17.0,"invy":0.043},"st":"NE"},"68138":{"l":"green","s":0,"r":[],"m":{"mos":0.366,"spy":0.072,"dom":9.0,"domy":-1.0,"invy":-0.211},"st":"NE"},"68105":{"l":"green","s":0,"r":[],"m":{"mos":0.557,"spy":0.221,"dom":18.0,"domy":-5.0,"invy":-0.025},"st":"NE"},"68501":{"l":"green","s":0,"r":[["insufficient_data",0]],"m":{"dom":1.0},"st":"NE"},"68104":{"l":"green","s":0,"r":[],"m":{"mos":0.355,"spy":0.019,"dom":25.0,"domy":5.0,"invy":-0.438},"st":"NE"},"68864":{"l":"green","s":1,"r":[["dom_stretching",223.0]],"m":{"spy":0.114,"dom":239.0,"domy":223.0},"st":"NE"},"68439":{"l":"green","s":1,"r":[["dom_stretching",105.0]],"m":{"spy":3.459,"dom":119.0,"domy":105.0},"st":"NE"},"68769":{"l":"green","s":0,"r":[],"m":{"spy":0.231,"dom":89.0,"domy":-7.0},"st":"NE"},"68430":{"l":"green","s":0,"r":[],"m":{"mos":0.4,"spy":0.056,"dom":110.5,"domy":28.5,"invy":-0.6},"st":"NE"},"68366":{"l":"green","s":1,"r":[["dom_stretching",231.0]],"m":{"spy":0.044,"dom":390.0,"domy":231.0},"st":"NE"},"69358":{"l":"yellow","s":3,"r":[["price_falling_fast",-0.083]],"m":{"mos":1.4,"spy":-0.083,"dom":31.0,"domy":-39.0,"invy":0.167},"st":"NE"},"69356":{"l":"green","s":0,"r":[["insufficient_data",1]],"m":{"mos":2.0,"dom":35.5},"st":"NE"},"68876":{"l":"red","s":4,"r":[["price_falling_fast",-0.066],["dom_stretching",153.5]],"m":{"mos":1.5,"spy":-0.066,"dom":188.5,"domy":153.5,"invy":-0.4},"st":"NE"},"68422":{"l":"yellow","s":3,"r":[["price_falling_fast",-0.373]],"m":{"spy":-0.373,"dom":23.0,"domy":-12.0},"st":"NE"},"68901":{"l":"yellow","s":3,"r":[["price_falling_fast",-0.066]],"m":{"mos":0.775,"spy":-0.066,"dom":35.0,"domy":0.0,"invy":-0.173},"st":"NE"},"68031":{"l":"yellow","s":3,"r":[["price_falling_fast",-0.279]],"m":{"mos":0.833,"spy":-0.279,"dom":37.0,"domy":-98.5,"invy":0.25},"st":"NE"},"68461":{"l":"green","s":1,"r":[["dom_stretching",27.0]],"m":{"mos":0.667,"spy":0.481,"dom":37.0,"domy":27.0,"invy":0.0},"st":"NE"},"68527":{"l":"green","s":1,"r":[["dom_stretching",43.0]],"m":{"mos":1.269,"spy":0.024,"dom":125.0,"domy":43.0,"invy":-0.298},"st":"NE"},"68803":{"l":"green","s":0,"r":[],"m":{"mos":1.0,"spy":0.034,"dom":44.0,"domy":11.0,"invy":0.109},"st":"NE"},"69357":{"l":"green","s":0,"r":[],"m":{"mos":1.2,"spy":0.1,"dom":42.0,"domy":-115.0,"invy":0.0},"st":"NE"},"68317":{"l":"yellow","s":3,"r":[["price_falling_fast",-0.427]],"m":{"mos":0.167,"spy":-0.427,"dom":22.0,"domy":-33.0,"invy":-0.8},"st":"NE"},"68765":{"l":"green","s":1,"r":[["dom_stretching",48.0]],"m":{"mos":1.0,"spy":0.746,"dom":90.0,"domy":48.0,"invy":-0.5},"st":"NE"},"68878":{"l":"green","s":0,"r":[["insufficient_data",0]],"m":{"dom":83.0},"st":"NE"},"68715":{"l":"green","s":0,"r":[],"m":{"mos":2.0,"spy":1.388,"dom":6.0,"domy":0.5,"invy":-0.667},"st":"NE"},"68768":{"l":"green","s":0,"r":[["insufficient_data",1]],"m":{"mos":1.0,"dom":148.0},"st":"NE"},"68504":{"l":"red","s":4,"r":[["price_falling_fast",-0.086],["dom_stretching",9.5]],"m":{"mos":0.472,"spy":-0.086,"dom":26.5,"domy":9.5,"invy":0.062},"st":"NE"},"68602":{"l":"green","s":0,"r":[],"m":{"spy":0.246,"dom":46.0,"domy":-65.0},"st":"NE"},"68456":{"l":"green","s":0,"r":[],"m":{"mos":2.0,"spy":1.145,"dom":2.0,"domy":-3.0,"invy":0.0},"st":"NE"},"68831":{"l":"green","s":0,"r":[["insufficient_data",1]],"m":{"mos":1.0,"dom":218.0},"st":"NE"},"68111":{"l":"green","s":1,"r":[["dom_stretching",24.5]],"m":{"mos":0.518,"spy":0.057,"dom":44.0,"domy":24.5,"invy":-0.173},"st":"NE"},"68752":{"l":"red","s":4,"r":[["price_falling_fast",-0.259],["dom_stretching",159.0]],"m":{"spy":-0.259,"dom":172.0,"domy":159.0},"st":"NE"},"69352":{"l":"green","s":0,"r":[["insufficient_data",0]],"m":{"dom":181.0},"st":"NE"},"68405":{"l":"green","s":1,"r":[["dom_stretching",32.5]],"m":{"mos":0.667,"spy":0.15,"dom":42.0,"domy":32.5,"invy":-0.5},"st":"NE"},"68022":{"l":"green","s":0,"r":[],"m":{"mos":0.631,"spy":-0.013,"dom":80.0,"domy":17.0,"invy":-0.511},"st":"NE"},"68070":{"l":"green","s":0,"r":[["insufficient_data",1]],"m":{"mos":0.667,"dom":16.0},"st":"NE"},"68008":{"l":"yellow","s":2,"r":[["price_falling",-0.033]],"m":{"mos":0.786,"spy":-0.033,"dom":30.5,"domy":5.5,"invy":-0.029},"st":"NE"},"68863":{"l":"red","s":5,"r":[["price_falling_fast",-0.756],["dom_stretching",156.0],["inventory_surge",1.0]],"m":{"mos":2.0,"spy":-0.756,"dom":248.0,"domy":156.0,"invy":1.0},"st":"NE"},"68419":{"l":"green","s":0,"r":[["insufficient_data",0]],"m":{"dom":5.0},"st":"NE"},"68048":{"l":"green","s":1,"r":[["dom_stretching",10.5]],"m":{"mos":0.729,"spy":0.073,"dom":29.0,"domy":10.5,"invy":-0.065},"st":"NE"},"69341":{"l":"green","s":1,"r":[["dom_stretching",15.0]],"m":{"mos":0.75,"spy":-0.005,"dom":43.0,"domy":15.0,"invy":-0.333},"st":"NE"},"68314":{"l":"green","s":0,"r":[["insufficient_data",0]],"m":{"dom":38.0},"st":"NE"},"69151":{"l":"green","s":0,"r":[["insufficient_data",0]],"m":{"dom":29.0},"st":"NE"},"68648":{"l":"green","s":0,"r":[["insufficient_data",1]],"m":{"mos":1.0,"dom":33.0},"st":"NE"},"68883":{"l":"green","s":0,"r":[],"m":{"mos":1.5,"spy":0.747,"dom":19.0,"domy":3.0,"invy":0.2},"st":"NE"},"68663":{"l":"red","s":4,"r":[["price_falling_fast",-0.635],["dom_stretching",65.0]],"m":{"mos":1.5,"spy":-0.635,"dom":106.0,"domy":65.0},"st":"NE"},"68872":{"l":"green","s":1,"r":[["dom_stretching",66.0]],"m":{"mos":1.0,"spy":2.765,"dom":90.0,"domy":66.0,"invy":-0.5},"st":"NE"},"68835":{"l":"green","s":0,"r":[["insufficient_data",0]],"m":{"dom":140.0},"st":"NE"},"68664":{"l":"green","s":0,"r":[["insufficient_data",0]],"m":{"dom":26.0},"st":"NE"},"68064":{"l":"yellow","s":3,"r":[["price_falling_fast",-0.429]],"m":{"mos":1.048,"spy":-0.429,"dom":44.0,"domy":-13.0,"invy":-0.083},"st":"NE"},"68866":{"l":"green","s":0,"r":[["insufficient_data",1]],"m":{"spy":-0.725},"st":"NE"},"68812":{"l":"green","s":1,"r":[["dom_stretching",5.0]],"m":{"spy":1.391,"dom":6.0,"domy":5.0},"st":"NE"},"68508":{"l":"green","s":0,"r":[],"m":{"mos":2.222,"spy":0.006,"dom":4.0,"domy":-32.5,"invy":0.176},"st":"NE"},"68364":{"l":"green","s":0,"r":[],"m":{"spy":1.467,"dom":2.0,"domy":-27.0},"st":"NE"},"68653":{"l":"red","s":4,"r":[["price_falling_fast",-0.173],["dom_stretching",46.5]],"m":{"mos":0.5,"spy":-0.173,"dom":64.5,"domy":46.5,"invy":-0.5},"st":"NE"},"68820":{"l":"red","s":4,"r":[["price_falling_fast",-0.719],["dom_stretching",173.0]],"m":{"spy":-0.719,"dom":210.0,"domy":173.0},"st":"NE"},"68827":{"l":"green","s":0,"r":[["insufficient_data",0]],"m":{"dom":17.0},"st":"NE"},"68133":{"l":"green","s":1,"r":[["dom_stretching",37.0]],"m":{"mos":0.463,"spy":0.081,"dom":52.0,"domy":37.0,"invy":-0.383},"st":"NE"},"68973":{"l":"red","s":4,"r":[["price_falling_fast",-0.31],["dom_stretching",118.0]],"m":{"spy":-0.31,"dom":195.0,"domy":118.0},"st":"NE"},"68643":{"l":"yellow","s":3,"r":[["price_falling_fast",-0.318]],"m":{"mos":2.0,"spy":-0.318,"dom":56.0,"domy":-50.0,"invy":0.0},"st":"NE"},"68336":{"l":"green","s":1,"r":[["dom_stretching",93.0]],"m":{"mos":1.0,"spy":0.42,"dom":95.0,"domy":93.0},"st":"NE"},"68512":{"l":"green","s":0,"r":[],"m":{"mos":0.205,"spy":0.03,"dom":15.0,"domy":-3.0,"invy":-0.7},"st":"NE"},"68945":{"l":"green","s":0,"r":[["insufficient_data",0]],"m":{"dom":35.0},"st":"NE"},"69143":{"l":"green","s":0,"r":[],"m":{"mos":0.75,"spy":0.692,"dom":49.0,"domy":14.0,"invy":0.5},"st":"NE"},"68304":{"l":"red","s":4,"r":[["price_falling_fast",-0.723],["dom_stretching",38.0]],"m":{"spy":-0.723,"dom":48.0,"domy":38.0},"st":"NE"},"69132":{"l":"green","s":0,"r":[["insufficient_data",0]],"m":{"dom":106.0},"st":"NE"},"68634":{"l":"green","s":0,"r":[["insufficient_data",1]],"m":{"mos":2.0,"dom":14.0},"st":"NE"},"68710":{"l":"green","s":1,"r":[["dom_stretching",101.0]],"m":{"spy":4.43,"dom":102.0,"domy":101.0},"st":"NE"},"68042":{"l":"green","s":0,"r":[["insufficient_data",0]],"m":{"dom":19.0},"st":"NE"},"68458":{"l":"green","s":0,"r":[["insufficient_data",0]],"m":{"dom":195.0},"st":"NE"},"68413":{"l":"green","s":0,"r":[["insufficient_data",1]],"m":{"mos":0.25,"dom":34.5},"st":"NE"},"69169":{"l":"green","s":0,"r":[["insufficient_data",0]],"m":{"dom":35.0},"st":"NE"},"68834":{"l":"green","s":0,"r":[["insufficient_data",1]],"m":{"mos":1.0,"dom":177.0},"st":"NE"},"68738":{"l":"green","s":0,"r":[["insufficient_data",0]],"m":{"dom":21.0},"st":"NE"},"68861":{"l":"green","s":0,"r":[],"m":{"spy":0.329,"dom":2.0,"domy":-8.0},"st":"NE"},"68330":{"l":"green","s":0,"r":[["insufficient_data",0]],"m":{"dom":143.0},"st":"NE"},"69170":{"l":"yellow","s":3,"r":[["price_falling_fast",-0.45]],"m":{"mos":1.0,"spy":-0.45,"dom":86.0,"domy":-171.0},"st":"NE"},"68309":{"l":"green","s":0,"r":[["insufficient_data",0]],"m":{"dom":22.0},"st":"NE"},"68531":{"l":"green","s":0,"r":[["insufficient_data",0]],"m":{"dom":5.0},"st":"NE"},"69167":{"l":"green","s":0,"r":[["insufficient_data",0]],"m":{"dom":10.0},"st":"NE"},"68728":{"l":"green","s":0,"r":[["insufficient_data",1]],"m":{"spy":0.697},"st":"NE"},"68403":{"l":"green","s":1,"r":[["dom_stretching",17.0]],"m":{"spy":0.885,"dom":59.0,"domy":17.0},"st":"NE"},"68948":{"l":"green","s":0,"r":[["insufficient_data",0]],"m":{"dom":113.0},"st":"NE"},"69355":{"l":"green","s":1,"r":[["dom_stretching",16.0]],"m":{"spy":0.452,"dom":36.0,"domy":16.0},"st":"NE"},"68757":{"l":"green","s":0,"r":[["insufficient_data",1]],"m":{"mos":1.0,"dom":61.5},"st":"NE"},"68732":{"l":"green","s":0,"r":[["insufficient_data",0]],"m":{"dom":21.0},"st":"NE"},"68785":{"l":"green","s":0,"r":[["insufficient_data",1]],"m":{"mos":1.0,"dom":66.0},"st":"NE"},"68925":{"l":"green","s":0,"r":[["insufficient_data",0]],"m":{"dom":47.0},"st":"NE"},"68026":{"l":"green","s":0,"r":[["insufficient_data",0]],"m":{"dom":21.0},"st":"NE"},"69346":{"l":"green","s":0,"r":[["insufficient_data",0]],"m":{"dom":259.0},"st":"NE"},"68848":{"l":"green","s":0,"r":[["insufficient_data",0]],"m":{"dom":245.0},"st":"NE"},"69171":{"l":"green","s":0,"r":[["insufficient_data",0]],"m":{"dom":189.0},"st":"NE"},"68747":{"l":"green","s":0,"r":[["insufficient_data",0]],"m":{"dom":46.0},"st":"NE"},"68381":{"l":"green","s":0,"r":[["insufficient_data",0]],"m":{"dom":37.0},"st":"NE"}}